Librarymu/__init__.py
Librarymu/my_class.py
gold33423320-0.0.1.dist-info/LICENCE.txt
gold33423320-0.0.1.dist-info/METADATA
gold33423320-0.0.1.dist-info/WHEEL
gold33423320-0.0.1.dist-info/top_level.txt
gold33423320-0.0.1.dist-info/RECORD
