Metadata-Version: 2.1
Name: gold33423320
Version: 0.0.1
Summary: UAS Daspro.
Home-page: https://github.com/rizalfarhan/gold33423320
Author: rizalfarhan
Author-email: <rizalfarhannanda@gmail.com>
License: MIT
Keywords: UAs,COY
Platform: UNKNOWN
Classifier: Development Status :: 1 - Planning
